setup.py
patiem_distributions/Binomialdistribution.py
patiem_distributions/Gaussiandistribution.py
patiem_distributions/Generaldistribution.py
patiem_distributions/__init__.py
patiem_distributions.egg-info/PKG-INFO
patiem_distributions.egg-info/SOURCES.txt
patiem_distributions.egg-info/dependency_links.txt
patiem_distributions.egg-info/not-zip-safe
patiem_distributions.egg-info/top_level.txt