Metadata-Version: 1.0
Name: patiem-distributions
Version: 0.1
Summary: Gaussian and Binomial distributions
Home-page: UNKNOWN
Author: Pati Em
Author-email: pp.mikulska@gmail.com
License: UNKNOWN
Platform: UNKNOWN
